glazzbocks/__init__.py
glazzbocks/diagnostics/__init__.py
glazzbocks/diagnostics/feature_diagnostics.py
glazzbocks/diagnostics/model_diagnostics.py
glazzbocks/eda/__init__.py
glazzbocks/eda/data_explorer.py
glazzbocks/interpreters/__init__.py
glazzbocks/interpreters/modelinterpreter.py
glazzbocks/pipeline/ML_pipeline.py
glazzbocks/pipeline/__init__.py
glazzbocks/reporting/__init__.py
glazzbocks/reporting/build.py
glazzbocks/reporting/config.py
glazzbocks/runtime/__init__.py
glazzbocks/runtime/__main__.py
glazzbocks/runtime/evaluate.py
glazzbocks/runtime/loaders.py
glazzbocks/runtime/schema.py
glazzbocks/utils/__init__.py
glazzbocks/utils/formatting.py
glazzbocks/utils/mlflow_tracker.py
glazzbocks/utils/plots.py
glazzbocks/utils/preprocessing.py
glazzbocks_ai/cli.py
glazzbocks_ai/demo_glazzbocks_ai.py
glazzbocks_ai/explain_with_gpt.py
glazzbocks_ai/export_facts.py
glazzbocks_ai/facts_from_glazzbocks.py
glazzbocks_ai/prompt_templates.py
glazzbocks_ai/app/main.py
glazzbocks_ai/outputs_llm/report_generator.py
glazzbocks_cli/__init__.py
glazzbocks_cli/__main__.py
glazzbocks_cli/main.py
glazzbocks_cli/commands/__init__.py
glazzbocks_cli/commands/azureml_pull.py
glazzbocks_cli/commands/databricks_pull.py
glazzbocks_cli/commands/report.py
glazzbocks-0.2.0.dist-info/METADATA
glazzbocks-0.2.0.dist-info/WHEEL
glazzbocks-0.2.0.dist-info/entry_points.txt
glazzbocks-0.2.0.dist-info/top_level.txt
glazzbocks-0.2.0.dist-info/RECORD
