Metadata-Version: 2.4
Name: glazzbocks
Version: 0.2.0
Summary: Glassbox ML with EDA, diagnostics, and AI-powered reporting
Home-page: https://github.com/JayMTea/glazzbocks
Author: Joshua Thompson
Author-email: jthompson@glazzbocks.com
License: MIT
Project-URL: Homepage, https://github.com/JayMTea/glazzbocks
Project-URL: Repository, https://github.com/JayMTea/glazzbocks
Project-URL: Issues, https://github.com/JayMTea/glazzbocks/issues
Requires-Python: >=3.9
Requires-Dist: pandas>=1.4
Requires-Dist: numpy>=1.22
Requires-Dist: scikit-learn>=1.1
Requires-Dist: matplotlib>=3.6
Requires-Dist: seaborn>=0.12
Requires-Dist: statsmodels>=0.13
Requires-Dist: jinja2>=3.1
Requires-Dist: xhtml2pdf>=0.2.13
Requires-Dist: joblib>=1.2
Requires-Dist: typer>=0.9
Requires-Dist: openai>=1.30.0
Provides-Extra: explain
Requires-Dist: shap>=0.41; extra == "explain"
Requires-Dist: umap-learn>=0.5.4; extra == "explain"
Provides-Extra: azureml
Requires-Dist: azure-ai-ml>=1.14.0; extra == "azureml"
Requires-Dist: azure-identity>=1.16.0; extra == "azureml"
Provides-Extra: dev
Requires-Dist: pytest>=7.0; extra == "dev"
Requires-Dist: black>=24.0; extra == "dev"
Requires-Dist: ruff>=0.4.0; extra == "dev"
Requires-Dist: build>=1.2.1; extra == "dev"
Requires-Dist: twine>=5.0.0; extra == "dev"
